<?xml version="1.0" encoding="UTF-8"?><virtualedges><edge type="GENERIC_FAKE"><source invoketype="instance" subsignature="java.lang.Object getSystemService(java.lang.String)"></source><targets><direct subsignature="void setListAdapter(android.widget.ListAdapter)" index="-1" target-position="base"></direct></targets></edge><edge type="GENERIC_FAKE"><source invoketype="instance" subsignature="android.database.sqlite.SQLiteDatabase getWritableDatabase()"></source><targets><direct subsignature="void onCreate(android.database.sqlite.SQLiteDatabase)" index="-1" target-position="base"></direct></targets></edge></virtualedges>